{
    "info": {
        "generated_on": "2017-12-03 08:41:42.057563",
        "slice": "228000-228999",
        "version": "v1"
    },
    "playlists": [
        {
            "name": "Rap en espa\u00f1ol",
            "pid": 3797,
            "num_tracks": 227,
            "num_followers": 15,
            "tracks": [
                {
                    "artist_name": "El Chojin",
                    "track_uri": "spotify:track:68PGUli5xICpRjozmXpBbQ",
                    "track_name": "El Mundo Sigue Girando"
                },
                {
                    "artist_name": "El Chojin",
                    "track_uri": "spotify:track:3FZDo3ehmRfeKpkwhsjn7A",
                    "track_name": "Rap Vs. Racismo - Con L\u00edrico, Santo, El Langui, Kase.O, Nach, Locus, Ose, Nervizzo, Sho Hai, Zatu, Gitano Anton, Tit\u00f3 y Xhelazz."
                },
                {
                    "artist_name": "El Chojin",
                    "track_uri": "spotify:track:7LSnzo3nZ1VdjBYDn5KpIJ",
                    "track_name": "Los PRO"
                },
                {
                    "artist_name": "El Chojin",
                    "track_uri": "spotify:track:18YCZgBpjvd7OiDzlqffj9",
                    "track_name": "R\u00ede Cuando Puedas"
                },
                {
                    "artist_name": "El Chojin",
                    "track_uri": "spotify:track:0EicBFnzqIUhX4T6Uw6zFh",
                    "track_name": "Nunca"
                },
                {
                    "artist_name": "El Chojin",
                    "track_uri": "spotify:track:79R0dPjVe5zcwQUJdIBvi3",
                    "track_name": "Ven, Ven"
                },
                {
                    "artist_name": "El Chojin",
                    "track_uri": "spotify:track:4pF1o8MC8Rx7VFI6zCTKov",
                    "track_name": "Apagado O Fuera De Cobertura"
                },
                {
                    "artist_name": "El Chojin",
                    "track_uri": "spotify:track:6N4hvFy1JTqdzgNVfBPQ8Q",
                    "track_name": "R\u00ede Cuando Puedas, Llora Cuando Lo Necesitas (Remix) [feat. Aute]"
                },
                {
                    "artist_name": "El Chojin",
                    "track_uri": "spotify:track:3rqwPqR1r5PYyjn1ouui89",
                    "track_name": "Estoy Cansao"
                },
                {
                    "artist_name": "Nach",
                    "track_uri": "spotify:track:2rctGpOJarwz28i4gtZD2R",
                    "track_name": "Viviendo"
                },
                {
                    "artist_name": "Nach",
                    "track_uri": "spotify:track:3kqlA4rbCESJPTE5RR3w3b",
                    "track_name": "Lo Estoy Intentando"
                },
                {
                    "artist_name": "Nach",
                    "track_uri": "spotify:track:3o4P6UdS8pttxJnXtZvvfg",
                    "track_name": "Leyenda"
                },
                {
                    "artist_name": "Nach",
                    "track_uri": "spotify:track:2O19TwNeRuHE6pNzoGecSX",
                    "track_name": "Gratis"
                },
                {
                    "artist_name": "Morodo",
                    "track_uri": "spotify:track:5gOwPlc6xJCmr3G2xUWWKQ",
                    "track_name": "Babilonia"
                },
                {
                    "artist_name": "Morodo",
                    "track_uri": "spotify:track:1fmqHIcOMcPXRGcucEayUK",
                    "track_name": "Yo Me Levanto"
                },
                {
                    "artist_name": "Nach",
                    "track_uri": "spotify:track:7A7PjCULsIDL1qD9WLX5mc",
                    "track_name": "Clandestinos"
                },
                {
                    "artist_name": "Nach",
                    "track_uri": "spotify:track:4lK1DpGjug4clQ3qr71Gkc",
                    "track_name": "El Camino del Guerrero"
                },
                {
                    "artist_name": "Morodo",
                    "track_uri": "spotify:track:549sreOYk5t50KhIN27i1N",
                    "track_name": "Decisiones al Filo"
                },
                {
                    "artist_name": "Nach",
                    "track_uri": "spotify:track:0DzhC1z9bkoYtMCt31xd2F",
                    "track_name": "El Hombre Que Siempre Estuvo All\u00ed"
                },
                {
                    "artist_name": "El Chojin",
                    "track_uri": "spotify:track:3lvWbSwndfZZCfhhopfVKI",
                    "track_name": "Unete A Mi Bando"
                },
                {
                    "artist_name": "El Chojin",
                    "track_uri": "spotify:track:1V1joYYe2Ru58ZoHPUMiiy",
                    "track_name": "Idiomas Distintos - Con Maika Sitt\u00e9"
                },
                {
                    "artist_name": "El Chojin",
                    "track_uri": "spotify:track:1UYxfnV5dn7zJgOz8OVDG6",
                    "track_name": "La Triste Historia Del Vecino De Arriba"
                },
                {
                    "artist_name": "Shotta",
                    "track_uri": "spotify:track:5yUR6jfhuKJNwUtYo52t2q",
                    "track_name": "Felicidad"
                },
                {
                    "artist_name": "El Chojin",
                    "track_uri": "spotify:track:3CDeVQSkOTvP2enjKo2GSL",
                    "track_name": "El Viaje"
                },
                {
                    "artist_name": "El Chojin",
                    "track_uri": "spotify:track:1mPv8ll1R7IZxv1n8aORYD",
                    "track_name": "Mi Odisea"
                },
                {
                    "artist_name": "SFDK",
                    "track_uri": "spotify:track:2i6iiyjKQ8JClv3NtNs0wm",
                    "track_name": "Bajo el Mismo Sol"
                },
                {
                    "artist_name": "SFDK",
                    "track_uri": "spotify:track:4aWrVBft7jEHE10aADrg4p",
                    "track_name": "Sin Miedo a Vivir"
                },
                {
                    "artist_name": "Green Valley",
                    "track_uri": "spotify:track:6ke06PT1SD6BQGAyOGMWxM",
                    "track_name": "Las Estrellas del Cielo (feat. Rayden)"
                },
                {
                    "artist_name": "SFDK",
                    "track_uri": "spotify:track:6haNScJR9trHxGYiaPIkMy",
                    "track_name": "Manos en el Aire"
                },
                {
                    "artist_name": "El Chojin",
                    "track_uri": "spotify:track:4UGd9GzHjZ1lK5LDZKiBUV",
                    "track_name": "El Reto"
                },
                {
                    "artist_name": "Rapsusklei",
                    "track_uri": "spotify:track:2THlf4MhAOjn2OpGCmOyUW",
                    "track_name": "A Fuego"
                },
                {
                    "artist_name": "Rapsusklei",
                    "track_uri": "spotify:track:41wVwJUWk1urN57CfAajMJ",
                    "track_name": "Cleopatra"
                },
                {
                    "artist_name": "A3Bandas",
                    "track_uri": "spotify:track:2VRU1VfKL8twTzFWmFhNsT",
                    "track_name": "A Tres Pasos y Medio"
                },
                {
                    "artist_name": "El Chojin",
                    "track_uri": "spotify:track:002l3HsdtprMRzXo4AwBOh",
                    "track_name": "Sexo"
                },
                {
                    "artist_name": "El Chojin",
                    "track_uri": "spotify:track:7ogYsoBGgyuzouEEZcrDjh",
                    "track_name": "Haz Que Cuente"
                },
                {
                    "artist_name": "El Chojin",
                    "track_uri": "spotify:track:23n5fgPB13LNbQdcqefU8c",
                    "track_name": "Paso A Paso"
                },
                {
                    "artist_name": "El Chojin",
                    "track_uri": "spotify:track:5fi4o34loVjI6iWu3HmX5Z",
                    "track_name": "Algo M\u00e1s Que M\u00fasica"
                },
                {
                    "artist_name": "El Chojin",
                    "track_uri": "spotify:track:1w3rwDmVM2mSPmxmk2jHfO",
                    "track_name": "Poder"
                },
                {
                    "artist_name": "El Chojin",
                    "track_uri": "spotify:track:4md9PUjVkhTlcL0AXkMOka",
                    "track_name": "Superh\u00e9roe Con Final (Bonus Track)"
                },
                {
                    "artist_name": "Rapsusklei",
                    "track_uri": "spotify:track:3th6ed2DVZLGU5NIEhGWNz",
                    "track_name": "Licor y Poes\u00eda"
                },
                {
                    "artist_name": "Rapsusklei",
                    "track_uri": "spotify:track:4Qlv2CpuKjPcYopLb6rm7G",
                    "track_name": "La Caja de Pandora"
                },
                {
                    "artist_name": "Green Valley",
                    "track_uri": "spotify:track:13nYJZLxyzNGxyGaHTKM4F",
                    "track_name": "Si No Te Tengo"
                },
                {
                    "artist_name": "El Chojin",
                    "track_uri": "spotify:track:53D3C6mAW0IangjvU7YCAf",
                    "track_name": "Antorchas y Rastrillos"
                },
                {
                    "artist_name": "El Chojin",
                    "track_uri": "spotify:track:7teIPpDwGm9lVZYBJR4oMV",
                    "track_name": "Supervivencia"
                },
                {
                    "artist_name": "El Chojin",
                    "track_uri": "spotify:track:2ItPYIVJ44FAIs7qxHTt0p",
                    "track_name": "Uh"
                },
                {
                    "artist_name": "El Chojin",
                    "track_uri": "spotify:track:2ErB8kWaNEAHBlLEWuqb3l",
                    "track_name": "Cara Sucia"
                },
                {
                    "artist_name": "El Chojin",
                    "track_uri": "spotify:track:0PD7j4x1PJDzUtTb7gUUlQ",
                    "track_name": "Estare Alli"
                },
                {
                    "artist_name": "SFDK",
                    "track_uri": "spotify:track:4xGGTtkiPmvMqUkqHZLMUr",
                    "track_name": "Lo Que Importa"
                },
                {
                    "artist_name": "SFDK",
                    "track_uri": "spotify:track:4EY4HFM9GVIDWj901x0NJx",
                    "track_name": "Los Chicos del Barrio"
                },
                {
                    "artist_name": "El Chojin",
                    "track_uri": "spotify:track:7066TZYHkHkR1mYYVFdIw6",
                    "track_name": "Te Llevo"
                },
                {
                    "artist_name": "El Chojin",
                    "track_uri": "spotify:track:7mkRqSq3hwbeD43m0dyNSG",
                    "track_name": "Bla Bla!"
                },
                {
                    "artist_name": "El Chojin",
                    "track_uri": "spotify:track:2UofLOpZ5gfJhwa1O8bfFZ",
                    "track_name": "Lo Que Me Piden"
                },
                {
                    "artist_name": "El Chojin",
                    "track_uri": "spotify:track:3XHvUbCkyUXplNFmXQ9IPB",
                    "track_name": "Si\u00e9ntense Y Disfruten (feat. Astrid Jones)"
                },
                {
                    "artist_name": "SFDK",
                    "track_uri": "spotify:track:3AcOeA0EOL7J59YVTFFnjS",
                    "track_name": "Lions"
                },
                {
                    "artist_name": "SFDK",
                    "track_uri": "spotify:track:5wEwIQHIpzfEQswCLp3HGM",
                    "track_name": "Esta Canci\u00f3n va Dedicada\u2026"
                },
                {
                    "artist_name": "Zatu",
                    "track_uri": "spotify:track:0ED7bKW8AGgPRAhbjOzD0n",
                    "track_name": "Ellos Van A Ver - Heavy Roots Rap Remix"
                },
                {
                    "artist_name": "SFDK",
                    "track_uri": "spotify:track:3qOtg4R7m5YPY35NfopC2Z",
                    "track_name": "Despacito Pero Voy"
                },
                {
                    "artist_name": "ZPU",
                    "track_uri": "spotify:track:3HkvI6ehqPImScZJ3fRQHv",
                    "track_name": "He Tenido un Sue\u00f1o"
                },
                {
                    "artist_name": "ZPU",
                    "track_uri": "spotify:track:4tZMwGtnnBFlEUs6s1FnLT",
                    "track_name": "David Contra Goliat - En Directo"
                },
                {
                    "artist_name": "ZPU",
                    "track_uri": "spotify:track:0eexfFvjObfdJoyW7ycrtN",
                    "track_name": "A Su Bola"
                },
                {
                    "artist_name": "Shotta",
                    "track_uri": "spotify:track:3g10e1iYPTfEB3NcT2cCyF",
                    "track_name": "One Love"
                },
                {
                    "artist_name": "Fyahbwoy",
                    "track_uri": "spotify:track:3FuVMP4hqP4HkKF3uaejD8",
                    "track_name": "Mala Fama (Remix) [feat. Dubosky]"
                },
                {
                    "artist_name": "Morodo",
                    "track_uri": "spotify:track:3ilr7hKnwSiJ71sMbk765C",
                    "track_name": "Burning Song"
                },
                {
                    "artist_name": "AMBKOR",
                    "track_uri": "spotify:track:3H2JYyr6vKljR6gkP86zcn",
                    "track_name": "Apagado"
                },
                {
                    "artist_name": "El Chojin",
                    "track_uri": "spotify:track:2hahu9d8Jpx0SKBqFL9XFe",
                    "track_name": "2005 Es el A\u00f1o"
                },
                {
                    "artist_name": "El Chojin",
                    "track_uri": "spotify:track:1BkZIH02jHD0BaICE5Sere",
                    "track_name": "Cosas Que Pasan"
                },
                {
                    "artist_name": "Rapsusklei",
                    "track_uri": "spotify:track:2tFlDk5EgjKG8jpAKNNCtm",
                    "track_name": "Con 35"
                },
                {
                    "artist_name": "Nach",
                    "track_uri": "spotify:track:4fc5Nv46nHQv1KiGGJRH6x",
                    "track_name": "El Hip-Hop Que S\u00e9"
                },
                {
                    "artist_name": "Fyahbwoy",
                    "track_uri": "spotify:track:2GH89kenJGi2oGLhHrTnbc",
                    "track_name": "Todo Lo Que Importa (feat. SFDK)"
                },
                {
                    "artist_name": "SFDK",
                    "track_uri": "spotify:track:6VnTJEOE3PlAG8plyOmldd",
                    "track_name": "Blondapetit"
                },
                {
                    "artist_name": "Nach",
                    "track_uri": "spotify:track:3nMgLAUPCOQvpcJRpvkJ2S",
                    "track_name": "Poes\u00eda De Guerra"
                },
                {
                    "artist_name": "Rapsusklei",
                    "track_uri": "spotify:track:19TGi5QfX6Xj1GuRvStcQ5",
                    "track_name": "Simbolos"
                },
                {
                    "artist_name": "Rapsusklei",
                    "track_uri": "spotify:track:1bUrKF0kIyAaOeDvBTmZwJ",
                    "track_name": "Dando y Perdiendo"
                },
                {
                    "artist_name": "Rapsusklei",
                    "track_uri": "spotify:track:5yxuc58yKeXMGcrwAATpbo",
                    "track_name": "Soledad"
                },
                {
                    "artist_name": "Nach",
                    "track_uri": "spotify:track:6gDDsfNGPCWBWSnL0rrY2H",
                    "track_name": "Rap Espa\u00f1ol"
                },
                {
                    "artist_name": "SFDK",
                    "track_uri": "spotify:track:0TVQ4e2Z0Cmd7Fiixj4Ofd",
                    "track_name": "Orgullo Banderillero"
                },
                {
                    "artist_name": "Rapsusklei",
                    "track_uri": "spotify:track:5QaKqIDvZG0m9MyxGY6VQp",
                    "track_name": "Take Note (Otra Vez)"
                },
                {
                    "artist_name": "Nach",
                    "track_uri": "spotify:track:4b6jzO3iSkDnzNBqKbXs3U",
                    "track_name": "Amor Libre"
                },
                {
                    "artist_name": "SFDK",
                    "track_uri": "spotify:track:32i9vuo1CdxinEp3VGPtX5",
                    "track_name": "Si el Rap Fuera un Juego"
                },
                {
                    "artist_name": "Rapsusklei",
                    "track_uri": "spotify:track:56evB0UmUEPaIKLPFYryXw",
                    "track_name": "Alas Rotas"
                },
                {
                    "artist_name": "Rapsusklei",
                    "track_uri": "spotify:track:3tVH0OlVDKPMfcEHhahAlx",
                    "track_name": "Una Lagrima"
                },
                {
                    "artist_name": "ZPU",
                    "track_uri": "spotify:track:7GHocYGuQbUFczcg0fiPXk",
                    "track_name": "Noches en Bcn - En Directo"
                },
                {
                    "artist_name": "Rapsusklei",
                    "track_uri": "spotify:track:2J5uO1P4jjdL7wQ1vFDtc1",
                    "track_name": "Fracaso o Victoria"
                },
                {
                    "artist_name": "ToteKing",
                    "track_uri": "spotify:track:6hQbwgOD6Xf0U5zdH1QL5w",
                    "track_name": "Mi Pol\u00edtica"
                },
                {
                    "artist_name": "Rapsusklei",
                    "track_uri": "spotify:track:4KDZpV3sagjrRN56HDky7B",
                    "track_name": "Siempre"
                },
                {
                    "artist_name": "Rapsusklei",
                    "track_uri": "spotify:track:03ArXagH33AwPi3rzcVKVh",
                    "track_name": "Mi Barrio"
                },
                {
                    "artist_name": "Rapsusklei",
                    "track_uri": "spotify:track:31Zh2GjIvLEHM6YK6paVgV",
                    "track_name": "Llamada en Espera"
                },
                {
                    "artist_name": "Rapsusklei",
                    "track_uri": "spotify:track:5ftgTKwi1Yg4cUvGhdNk06",
                    "track_name": "En Busca"
                },
                {
                    "artist_name": "Almighty",
                    "track_uri": "spotify:track:1CpHuqnduaIxN1qvsiZndy",
                    "track_name": "Personalidades (feat. Farruko)"
                },
                {
                    "artist_name": "Gordo Master",
                    "track_uri": "spotify:track:4KEHkaAgBRg6UBn236mVYl",
                    "track_name": "Vamos Sin N\u00e1 (feat. Rapsuskley)"
                },
                {
                    "artist_name": "Gordo Master",
                    "track_uri": "spotify:track:2Jpidb5qZR3jEVIO7zXXur",
                    "track_name": "Gm"
                },
                {
                    "artist_name": "ZPU",
                    "track_uri": "spotify:track:5if3JzeUPoXRd9eV2ajfkX",
                    "track_name": "Noches en BCN"
                },
                {
                    "artist_name": "ZPU",
                    "track_uri": "spotify:track:1dAAWMv9i58UqjME1jQv6x",
                    "track_name": "Estira los Dedos"
                },
                {
                    "artist_name": "ZPU",
                    "track_uri": "spotify:track:6U0iWrr55eqY7F509DHYIP",
                    "track_name": "El Silencio de Dios - En Directo"
                },
                {
                    "artist_name": "ZPU",
                    "track_uri": "spotify:track:6zDIKSOJgEvegZJDRi3T8o",
                    "track_name": "Tod@s Sois Iguales"
                },
                {
                    "artist_name": "ZPU",
                    "track_uri": "spotify:track:7sX81rjpSNqTGuOuk0imQ0",
                    "track_name": "Tranqui"
                },
                {
                    "artist_name": "ZPU",
                    "track_uri": "spotify:track:4bjTh9o80knO3c9TnLKdpD",
                    "track_name": "Sobran las Palabras - En Directo"
                },
                {
                    "artist_name": "ZPU",
                    "track_uri": "spotify:track:7I1UnDUo2fSlk8yO9oxz2G",
                    "track_name": "Infamia"
                },
                {
                    "artist_name": "ZPU",
                    "track_uri": "spotify:track:5rl5V2QwgQtSIoIaZpzj0S",
                    "track_name": "De 4 en 4"
                },
                {
                    "artist_name": "ZPU",
                    "track_uri": "spotify:track:7MYez1C9X1ZSmcSSZR7IYL",
                    "track_name": "5 Razones"
                },
                {
                    "artist_name": "Los Aldeanos",
                    "track_uri": "spotify:track:2u5xCBl93ShUWZtKmGwws5",
                    "track_name": "Arrurru"
                },
                {
                    "artist_name": "El B.",
                    "track_uri": "spotify:track:1iiUZdJAS54iMeAWfTAico",
                    "track_name": "La Naranja Se Pico"
                },
                {
                    "artist_name": "Los Aldeanos",
                    "track_uri": "spotify:track:6eHYboyZNcYvvVWxO0TuMp",
                    "track_name": "Mandamos a Parar"
                },
                {
                    "artist_name": "Los Aldeanos",
                    "track_uri": "spotify:track:7k41PRxOWxd0FIxqs18Jey",
                    "track_name": "El Rap es Guerra"
                },
                {
                    "artist_name": "Los Aldeanos",
                    "track_uri": "spotify:track:3eutydEVrDQzYAURhIdi9s",
                    "track_name": "La Vida"
                },
                {
                    "artist_name": "Los Aldeanos",
                    "track_uri": "spotify:track:0Kvh8iVCcUPpY8rMo7MzvL",
                    "track_name": "Ninito Cubano"
                },
                {
                    "artist_name": "Los Aldeanos",
                    "track_uri": "spotify:track:5gmLpD14yE9d55tLCZ0ugo",
                    "track_name": "La Clase"
                },
                {
                    "artist_name": "Los Aldeanos",
                    "track_uri": "spotify:track:5UTZ7uRs6wPn9vaIwtjZIC",
                    "track_name": "K Charra"
                },
                {
                    "artist_name": "Los Aldeanos",
                    "track_uri": "spotify:track:0lYrK9aKTs2v8TCYjwLSRT",
                    "track_name": "Fuego"
                },
                {
                    "artist_name": "Los Aldeanos",
                    "track_uri": "spotify:track:0dVrAQSCd6KWvRr9m3BYPV",
                    "track_name": "Todos Para Una"
                },
                {
                    "artist_name": "Los Aldeanos",
                    "track_uri": "spotify:track:5sIgCo3VeEmlOLItPkPCIl",
                    "track_name": "A Veces Sueno"
                },
                {
                    "artist_name": "Los Aldeanos",
                    "track_uri": "spotify:track:2nHeQzpeEJ07MOfsh2Kvwz",
                    "track_name": "Mi Hermano o Yo 2"
                },
                {
                    "artist_name": "\u00d1ejo",
                    "track_uri": "spotify:track:5I1fBcs6zrBcydj9QUMItG",
                    "track_name": "Y Si la Ves"
                },
                {
                    "artist_name": "Los Aldeanos",
                    "track_uri": "spotify:track:7yWHnMxuVApngpjC6RvRK4",
                    "track_name": "Mi Hermano o Yo"
                },
                {
                    "artist_name": "Al2 El Aldeano",
                    "track_uri": "spotify:track:1M2eVy8VkzlCpyRJaYb5eE",
                    "track_name": "1na Hora de Vida"
                },
                {
                    "artist_name": "Al2 El Aldeano",
                    "track_uri": "spotify:track:7GtUSyNaubaxVvY7jINtBy",
                    "track_name": "Por Si Ma\u00f1ana no Estoy (feat. Escuadr\u00f3n Patriota)"
                },
                {
                    "artist_name": "Al2 El Aldeano",
                    "track_uri": "spotify:track:5TgcGTb1lfLFe20mXGpdLP",
                    "track_name": "El Casete de tu Vida"
                },
                {
                    "artist_name": "Al2 El Aldeano",
                    "track_uri": "spotify:track:2VXeEbuvtsm9nuaV0VYfoM",
                    "track_name": "Fumando La Vida"
                },
                {
                    "artist_name": "Al2 El Aldeano",
                    "track_uri": "spotify:track:1HKdm7rvw83v3fgtvwwa5J",
                    "track_name": "Aldito el Gusanito"
                },
                {
                    "artist_name": "Al2 El Aldeano",
                    "track_uri": "spotify:track:5ExrMhGta9YKr5x0PrfGWE",
                    "track_name": "Hermanos"
                },
                {
                    "artist_name": "Al2 El Aldeano",
                    "track_uri": "spotify:track:1CU281C3zy3yVIQ97aCiFs",
                    "track_name": "Mima"
                },
                {
                    "artist_name": "Al2 El Aldeano",
                    "track_uri": "spotify:track:6jlSGDBPYQAvvHtAiRyiqz",
                    "track_name": "Tiranosaurio"
                },
                {
                    "artist_name": "Al2 El Aldeano",
                    "track_uri": "spotify:track:5HsETWmOnlcCNpY2hg53Ic",
                    "track_name": "Un Secretico"
                },
                {
                    "artist_name": "Al2 El Aldeano",
                    "track_uri": "spotify:track:5wwjSd81UUaczTTuf5BjGM",
                    "track_name": "La Gente Cambia de la Noche a la Ma\u00f1ana"
                },
                {
                    "artist_name": "Shotta",
                    "track_uri": "spotify:track:0cBHtLKW4Gj38DSsbS3UZ7",
                    "track_name": "Hardcore"
                },
                {
                    "artist_name": "Shotta",
                    "track_uri": "spotify:track:4k9rolqSF2xWZgB14esCig",
                    "track_name": "S\u00e9"
                },
                {
                    "artist_name": "Al2 El Aldeano",
                    "track_uri": "spotify:track:2R9uYIfXfB8e1VvjYlekGS",
                    "track_name": "Un Motivo"
                },
                {
                    "artist_name": "Al2 El Aldeano",
                    "track_uri": "spotify:track:0l5TxrjlR6WnFKwh2xgyM3",
                    "track_name": "Freaky Incomprendido"
                },
                {
                    "artist_name": "Al2 El Aldeano",
                    "track_uri": "spotify:track:4vGAj3bGSzbMREkjiqcgLU",
                    "track_name": "Mam\u00e1"
                },
                {
                    "artist_name": "Al2 El Aldeano",
                    "track_uri": "spotify:track:4AdSDTo5OjG1FHv9VFzm4c",
                    "track_name": "Tu Eres Mi E.T."
                },
                {
                    "artist_name": "Al2 El Aldeano",
                    "track_uri": "spotify:track:6vgMZok7hwPa265ITfjwgx",
                    "track_name": "Nos Achicharraron"
                },
                {
                    "artist_name": "Al2 El Aldeano",
                    "track_uri": "spotify:track:4XLU3m1guLMUdG5GrRpGHm",
                    "track_name": "Intro"
                },
                {
                    "artist_name": "Al2 El Aldeano",
                    "track_uri": "spotify:track:4GV3k6FWxBJ1rgM6fegNU0",
                    "track_name": "Amiga Mia"
                },
                {
                    "artist_name": "ToteKing",
                    "track_uri": "spotify:track:3YndhKKjvxreAqHCfHLbiD",
                    "track_name": "Todo el D\u00eda Barras"
                },
                {
                    "artist_name": "ToteKing",
                    "track_uri": "spotify:track:5TdQV0qU6mLaIUtWmkgcAm",
                    "track_name": "Naaaah Naaah Nahhh"
                },
                {
                    "artist_name": "ToteKing",
                    "track_uri": "spotify:track:7fXdnpc2x7PLMCRS3KE4PX",
                    "track_name": "Muchas Gracias"
                },
                {
                    "artist_name": "ToteKing",
                    "track_uri": "spotify:track:0JgnYCPnkwFogIjvph0sQk",
                    "track_name": "Voy A...."
                },
                {
                    "artist_name": "Sharif",
                    "track_uri": "spotify:track:6qZXh7qBO6bUJB4wuASt3R",
                    "track_name": "El Callej\u00f3n de los Milagros"
                },
                {
                    "artist_name": "Sharif",
                    "track_uri": "spotify:track:4gG6PnQikLM5ocJtBf6jBU",
                    "track_name": "100 Frases"
                },
                {
                    "artist_name": "Sharif",
                    "track_uri": "spotify:track:3BHk6fEh6nSdlFpdsEq007",
                    "track_name": "Flor de Cerezo"
                },
                {
                    "artist_name": "Sharif",
                    "track_uri": "spotify:track:0jht9QQhRdBnkATKjVJVWU",
                    "track_name": "Perdonar y Agradecer"
                },
                {
                    "artist_name": "Sharif",
                    "track_uri": "spotify:track:2Yl1WZchKgFP7N2wiZGpjf",
                    "track_name": "Sobre Los M\u00e1rgenes"
                },
                {
                    "artist_name": "Sharif",
                    "track_uri": "spotify:track:54j6k8HS6kGDVJHirqntRX",
                    "track_name": "Agua Entre Las Manos"
                },
                {
                    "artist_name": "Sharif",
                    "track_uri": "spotify:track:7JRTH0hKYGGXrItYOojarc",
                    "track_name": "M\u00fasica Bendita"
                },
                {
                    "artist_name": "Sharif",
                    "track_uri": "spotify:track:5t3K7F3i1Ifxw1sdLr87QJ",
                    "track_name": "El Exilio De Mi Folio"
                },
                {
                    "artist_name": "Al2 El Aldeano",
                    "track_uri": "spotify:track:5L1cYp9DZjpF7pqEHT1jv1",
                    "track_name": "Tu No Crecistes"
                },
                {
                    "artist_name": "Al2 El Aldeano",
                    "track_uri": "spotify:track:4rpnUIW5vNO3N8L7QzJ5U1",
                    "track_name": "Hasta Que Sucedio"
                },
                {
                    "artist_name": "Al2 El Aldeano",
                    "track_uri": "spotify:track:4lymMS7ST8wxL3cd6biHu6",
                    "track_name": "Represento"
                },
                {
                    "artist_name": "Al2 El Aldeano",
                    "track_uri": "spotify:track:5YFdOTOwMj2p38Zlu5bAY7",
                    "track_name": "Lastima"
                },
                {
                    "artist_name": "995",
                    "track_uri": "spotify:track:04kdiOvVb2dRWVLVLjPfwy",
                    "track_name": "Sois Todos Unos Cursis"
                },
                {
                    "artist_name": "Al2 El Aldeano",
                    "track_uri": "spotify:track:7ePKzVzDNasXHR6eyFkr9J",
                    "track_name": "Vereda Tropical"
                },
                {
                    "artist_name": "Al2 El Aldeano",
                    "track_uri": "spotify:track:56tKLX5xzdBSm4vHondN0a",
                    "track_name": "La Bandera de tu Alma"
                },
                {
                    "artist_name": "Al2 El Aldeano",
                    "track_uri": "spotify:track:4lYoY5ZXsD0K9IjurU8Q5a",
                    "track_name": "La Papa"
                },
                {
                    "artist_name": "El B.",
                    "track_uri": "spotify:track:6W2eHDjmn4ukOkG6cFlP7O",
                    "track_name": "Siempre Me Quedara"
                },
                {
                    "artist_name": "El B.",
                    "track_uri": "spotify:track:3b5b9QSdk3A3BelV5wBoJp",
                    "track_name": "Princesita"
                },
                {
                    "artist_name": "El B.",
                    "track_uri": "spotify:track:1ePYdlHPDNQ6Hf0YHFNncE",
                    "track_name": "Soy Ese"
                },
                {
                    "artist_name": "El B.",
                    "track_uri": "spotify:track:4r69x7RBW3PZoGobNPkT2J",
                    "track_name": "Viva Cuba Libre"
                },
                {
                    "artist_name": "Los Aldeanos",
                    "track_uri": "spotify:track:6Vw2g1lzPoe9hxKn0tsk8a",
                    "track_name": "Fue un Placer"
                },
                {
                    "artist_name": "Los Aldeanos",
                    "track_uri": "spotify:track:2P56OM3uU7YT3TgEpzkAvX",
                    "track_name": "Poesia"
                },
                {
                    "artist_name": "Canserbero",
                    "track_uri": "spotify:track:1VIQPJc3fGfX23S6SD651l",
                    "track_name": "Stupid Love Story"
                },
                {
                    "artist_name": "Al2 El Aldeano",
                    "track_uri": "spotify:track:6re7ugECbt9bttbgfkoIIk",
                    "track_name": "Alma"
                },
                {
                    "artist_name": "Al2 El Aldeano",
                    "track_uri": "spotify:track:5DQ6KHVzncYIrbvDsZB3aq",
                    "track_name": "Las Kras"
                },
                {
                    "artist_name": "Al2 El Aldeano",
                    "track_uri": "spotify:track:4yw3rQ0cOIDxc7Y09Qvy38",
                    "track_name": "Manual Para Hacer Una Knci\u00f3n"
                },
                {
                    "artist_name": "Al2 El Aldeano",
                    "track_uri": "spotify:track:1D1cx7rD6NRFFbaFYgFF2u",
                    "track_name": "Hay Gentes Que se Creen Cosas y Cosas que se Creen Gentes"
                },
                {
                    "artist_name": "Al2 El Aldeano",
                    "track_uri": "spotify:track:4G2c6MyS9q0mFgFuz3Qh7M",
                    "track_name": "Respuesta"
                },
                {
                    "artist_name": "Norick",
                    "track_uri": "spotify:track:4reO3bmQddoGsM0iYoIpo4",
                    "track_name": "Karma"
                },
                {
                    "artist_name": "Rayden",
                    "track_uri": "spotify:track:13zRSGRgufFRfHJMMc35ES",
                    "track_name": "Sastre de Sonrisas"
                },
                {
                    "artist_name": "Brock Ansiolitiko",
                    "track_uri": "spotify:track:3xTDmpUY7KzXQMHNJGMSvZ",
                    "track_name": "Eternidad"
                },
                {
                    "artist_name": "Rapsusklei",
                    "track_uri": "spotify:track:2IMfsmbgGMXAowP5oGl3D7",
                    "track_name": "Barcos de Papel"
                },
                {
                    "artist_name": "ZPU",
                    "track_uri": "spotify:track:4UeCYIRcN087p1s0ollALO",
                    "track_name": "Ahora Qui\u00e9n"
                },
                {
                    "artist_name": "ZPU",
                    "track_uri": "spotify:track:5ETLkCOSHeJjJT4Ga542fW",
                    "track_name": "El Silencio de Dios"
                },
                {
                    "artist_name": "ZPU",
                    "track_uri": "spotify:track:6dE84dBmjoSHNk1fs6ApDS",
                    "track_name": "\u00daltima Llamada"
                },
                {
                    "artist_name": "ZPU",
                    "track_uri": "spotify:track:2TX8EDT3X9FpMHhjYGoajc",
                    "track_name": "Mi Caja de los Truenos"
                },
                {
                    "artist_name": "ZPU",
                    "track_uri": "spotify:track:5rGXHIBXrINjQuab5zLLKM",
                    "track_name": "Mi Mejor Amigo"
                },
                {
                    "artist_name": "Rapsusklei",
                    "track_uri": "spotify:track:1VYCCm2gVR059SJlPx1tiz",
                    "track_name": "Maktub"
                },
                {
                    "artist_name": "Shotta",
                    "track_uri": "spotify:track:2wMcBoEziAg6f4mWs1GKnq",
                    "track_name": "Hay Que Vivir"
                },
                {
                    "artist_name": "Shotta",
                    "track_uri": "spotify:track:38r4cVlP5xBZuYyxCJiH1G",
                    "track_name": "Hola"
                },
                {
                    "artist_name": "Rapsusklei",
                    "track_uri": "spotify:track:6VfKQydYXnM5xT3jVr5sw9",
                    "track_name": "G\u00e9nesis"
                },
                {
                    "artist_name": "Rapsusklei",
                    "track_uri": "spotify:track:4uq2X83RgRmjBD16iAc2kD",
                    "track_name": "Per la Luna"
                },
                {
                    "artist_name": "Rapsusklei",
                    "track_uri": "spotify:track:7KxbwbhfkDyEeJdi7d4kGy",
                    "track_name": "Canci\u00f3n a la Esperanza"
                },
                {
                    "artist_name": "Rapsusklei",
                    "track_uri": "spotify:track:4W4SiBrMa60zgIidDSukOL",
                    "track_name": "A Tres Estaciones del Invierno"
                },
                {
                    "artist_name": "Rapsusklei",
                    "track_uri": "spotify:track:40NI6iS8GO4kO9LkLiHoM9",
                    "track_name": "60 Veces por Minuto"
                },
                {
                    "artist_name": "Al2 El Aldeano",
                    "track_uri": "spotify:track:4rpnUIW5vNO3N8L7QzJ5U1",
                    "track_name": "Hasta Que Sucedio"
                },
                {
                    "artist_name": "Rapsusklei",
                    "track_uri": "spotify:track:46RHz0aqfrwRmGMdEgenL4",
                    "track_name": "Tantas Veces Dijeron"
                },
                {
                    "artist_name": "Rapsusklei",
                    "track_uri": "spotify:track:4tBVE8IZFKMksNo3S28kC6",
                    "track_name": "Los Ojos Cerrados"
                },
                {
                    "artist_name": "Rapsusklei",
                    "track_uri": "spotify:track:6KRCpNwZF0licOnlLhtiju",
                    "track_name": "No Miro Atr\u00e1s"
                },
                {
                    "artist_name": "Rapsusklei",
                    "track_uri": "spotify:track:1CVmeKOoWE6fnME1xf2ffQ",
                    "track_name": "En Busca de la Felicidad"
                },
                {
                    "artist_name": "Rapsusklei",
                    "track_uri": "spotify:track:4kSAmODaiZao7EU3QBPSr4",
                    "track_name": "Abecedario - Outro"
                },
                {
                    "artist_name": "Shotta",
                    "track_uri": "spotify:track:6sb7fgcLmFdpGjF8Q5eBfQ",
                    "track_name": "Amigos"
                },
                {
                    "artist_name": "Shotta",
                    "track_uri": "spotify:track:7tIGUistCHi5tdtVz65rAh",
                    "track_name": "T\u00fa"
                },
                {
                    "artist_name": "Shotta",
                    "track_uri": "spotify:track:7oynR4UYzl80bdE5o8sjww",
                    "track_name": "Ya No Siento Nada"
                },
                {
                    "artist_name": "Sh\u00e9",
                    "track_uri": "spotify:track:11BCNO3x3Jq07a9aC9ocQj",
                    "track_name": "No hay derecho"
                },
                {
                    "artist_name": "Rayden",
                    "track_uri": "spotify:track:24nQS0f39ZmbrmssfQIrBa",
                    "track_name": "\u00bfPor Que?"
                },
                {
                    "artist_name": "Morodo",
                    "track_uri": "spotify:track:7DjU18MR4FiUmst1Ovw3BZ",
                    "track_name": "Que Vas a Hacer?"
                },
                {
                    "artist_name": "Fyahbwoy",
                    "track_uri": "spotify:track:1y9NczKWbgodnLtBKf1D1A",
                    "track_name": "Peleando Con Dios"
                },
                {
                    "artist_name": "Fyahbwoy",
                    "track_uri": "spotify:track:68itNLn2Br8RHJ42zLmnol",
                    "track_name": "Guerras Del Odio"
                },
                {
                    "artist_name": "Fyahbwoy",
                    "track_uri": "spotify:track:0Za4LPtvBLRdaEQWMp0xhU",
                    "track_name": "No Estamos Creyendo (feat. Rapsusklei & Karty er nene)"
                },
                {
                    "artist_name": "Nengo Flow",
                    "track_uri": "spotify:track:3kWMm2iFysQf0j1857c1vk",
                    "track_name": "Baby Lover"
                },
                {
                    "artist_name": "Rapsusklei",
                    "track_uri": "spotify:track:6f4bbQnt1m7aDF8735e7Nz",
                    "track_name": "Put Your Hands Up"
                },
                {
                    "artist_name": "Al2 El Aldeano",
                    "track_uri": "spotify:track:0uOV7Ziu3PujXspemNAsul",
                    "track_name": "Yo Se"
                },
                {
                    "artist_name": "Al2 El Aldeano",
                    "track_uri": "spotify:track:5LLxNQuvWOQ43QmgOua8zm",
                    "track_name": "No Puedo Olvidarlo"
                },
                {
                    "artist_name": "Canserbero",
                    "track_uri": "spotify:track:2auNjgM4xIOANxtZT4Xe9z",
                    "track_name": "Pensando en Ti"
                },
                {
                    "artist_name": "Canserbero",
                    "track_uri": "spotify:track:3grYJajZn99R9PyPNIyz8A",
                    "track_name": "Perdiendo la Fe"
                },
                {
                    "artist_name": "Canserbero",
                    "track_uri": "spotify:track:7t3OAX7jsyh0frNxcj9XUb",
                    "track_name": "Es \u00c9pico"
                },
                {
                    "artist_name": "Gabylonia",
                    "track_uri": "spotify:track:3slT9zaAwHISs6T2485OKJ",
                    "track_name": "\u00c1ngeles"
                },
                {
                    "artist_name": "Canserbero",
                    "track_uri": "spotify:track:2gjuqCRGeK8Du190tLZN41",
                    "track_name": "PROlogo"
                },
                {
                    "artist_name": "Canserbero",
                    "track_uri": "spotify:track:1gTYZRPClEbTJKuxjli9rX",
                    "track_name": "Ni de Oro ni de Goldfield"
                },
                {
                    "artist_name": "Canserbero",
                    "track_uri": "spotify:track:04eL7Mun5wCThY3P37onK4",
                    "track_name": "CANbiate"
                },
                {
                    "artist_name": "Canserbero",
                    "track_uri": "spotify:track:7DMePP45IaGHRVFYDmmhqU",
                    "track_name": "El Mundo ya Se Acab\u00f3"
                },
                {
                    "artist_name": "Canserbero",
                    "track_uri": "spotify:track:1cB7ICDw725ZYDC7mkXxF2",
                    "track_name": "CANci\u00f3n de la Prisi\u00f3n"
                },
                {
                    "artist_name": "Canserbero",
                    "track_uri": "spotify:track:1T0HbAbDhzUC2GWqliCneC",
                    "track_name": "CAN you hear it"
                },
                {
                    "artist_name": "Canserbero",
                    "track_uri": "spotify:track:5O6DSCerJDXLs6M0j5d8E5",
                    "track_name": "Gu\u00eda Para la Acci\u00f3n"
                },
                {
                    "artist_name": "Canserbero",
                    "track_uri": "spotify:track:2MNMfgodY5q7nLbv1ZeJ2r",
                    "track_name": "CANpesino"
                },
                {
                    "artist_name": "Canserbero",
                    "track_uri": "spotify:track:5DyaEWda6mRFoRFp7WVQ2W",
                    "track_name": "Rialaif"
                },
                {
                    "artist_name": "Canserbero",
                    "track_uri": "spotify:track:44dkhB684HPxosPgaGNndR",
                    "track_name": "Perd\u00f3n"
                },
                {
                    "artist_name": "Canserbero",
                    "track_uri": "spotify:track:3Z04bvI9rEqh3fzF9c4gGJ",
                    "track_name": "As\u00ed Mismo"
                },
                {
                    "artist_name": "Canserbero",
                    "track_uri": "spotify:track:6jBIyH6GoPCc69hrHlHDAv",
                    "track_name": "Corazones de Piedra"
                },
                {
                    "artist_name": "Canserbero",
                    "track_uri": "spotify:track:3irIdzpAQeaVCB0u0nXr7n",
                    "track_name": "La Voz"
                },
                {
                    "artist_name": "Canserbero",
                    "track_uri": "spotify:track:6WYacaEMFuwj3sRtQK2Qq6",
                    "track_name": "Visiones"
                },
                {
                    "artist_name": "Canserbero",
                    "track_uri": "spotify:track:49gJfcGEUmTt3tJOYxAW3W",
                    "track_name": "Advertencia"
                },
                {
                    "artist_name": "Canserbero",
                    "track_uri": "spotify:track:2pBtRhLBQ6GzAQO6W4LJB5",
                    "track_name": "Ep\u00edlogo"
                },
                {
                    "artist_name": "Canserbero",
                    "track_uri": "spotify:track:5O6DSCerJDXLs6M0j5d8E5",
                    "track_name": "Gu\u00eda Para la Acci\u00f3n"
                },
                {
                    "artist_name": "Canserbero",
                    "track_uri": "spotify:track:447r2keRxpkINmWYp83MlH",
                    "track_name": "Maquiav\u00e9lico"
                },
                {
                    "artist_name": "Canserbero",
                    "track_uri": "spotify:track:1FPr4bsL5xaF4pRHoxvfJf",
                    "track_name": "Cuando Vayas Conmigo"
                },
                {
                    "artist_name": "Canserbero",
                    "track_uri": "spotify:track:0Ao7UyZ0IcKH9WQitKd0EL",
                    "track_name": "Ma\u00f1ana Ser\u00e1 Otro D\u00eda"
                },
                {
                    "artist_name": "Porta",
                    "track_uri": "spotify:track:3dLmRHahSD8GqeJ6iy755G",
                    "track_name": "La Bella Y La Bestia (Con Norykko)"
                },
                {
                    "artist_name": "El Chojin",
                    "track_uri": "spotify:track:0wZMiRXKitvHFhcSqZriAe",
                    "track_name": "Soy y No Soy"
                }
            ],
            "num_edits": 109,
            "duration_ms": 58855026,
            "num_artists": 29
        },
        {
            "name": "Ranch",
            "pid": 3798,
            "num_tracks": 182,
            "num_followers": 26,
            "tracks": [
                {
                    "artist_name": "Bart Crow",
                    "track_uri": "spotify:track:53lnXxETBx3eRxFG30F3v1",
                    "track_name": "Wear My Ring"
                },
                {
                    "artist_name": "Turnpike Troubadours",
                    "track_uri": "spotify:track:62EcdBCqjB62CxnhgBkkJT",
                    "track_name": "7 & 7"
                },
                {
                    "artist_name": "Turnpike Troubadours",
                    "track_uri": "spotify:track:3BXe9ZWHc05Ejzo51NuQVG",
                    "track_name": "Whole Damn Town"
                },
                {
                    "artist_name": "Bart Crow Band",
                    "track_uri": "spotify:track:100o388NiGWx3JozbPnm85",
                    "track_name": "Run with the Devil"
                },
                {
                    "artist_name": "Turnpike Troubadours",
                    "track_uri": "spotify:track:0FuaxhI17w2hPRdN4sDSaG",
                    "track_name": "Kansas City Southern"
                },
                {
                    "artist_name": "Casey Donahew",
                    "track_uri": "spotify:track:5QoCwYZPqruGNKWFZCzwJM",
                    "track_name": "High"
                },
                {
                    "artist_name": "Stoney LaRue",
                    "track_uri": "spotify:track:6mdE6zjIRP9RFe9nSMMW9U",
                    "track_name": "Look At Me Fly"
                },
                {
                    "artist_name": "Emory Quinn",
                    "track_uri": "spotify:track:1TzLw85hd7gvalriIbzXtd",
                    "track_name": "Falling Down Again"
                },
                {
                    "artist_name": "Blackberry Smoke",
                    "track_uri": "spotify:track:2I3yLahXF64kGibDadEUtz",
                    "track_name": "Pretty Little Lie"
                },
                {
                    "artist_name": "George Strait",
                    "track_uri": "spotify:track:1J02p0AlYptTfos2M3hLW6",
                    "track_name": "Cowboys Like Us"
                },
                {
                    "artist_name": "Alan Jackson",
                    "track_uri": "spotify:track:7g9YLSMScVdHQNPyUijl8S",
                    "track_name": "Designated Drinker - A Duet With George Strait"
                },
                {
                    "artist_name": "Casey Donahew",
                    "track_uri": "spotify:track:3HQMDHF7Uahn1RCd93l0rh",
                    "track_name": "Double-Wide Dream"
                },
                {
                    "artist_name": "Turnpike Troubadours",
                    "track_uri": "spotify:track:3l4cnZdtNbVZgV3ICYh1Ni",
                    "track_name": "Every Girl"
                },
                {
                    "artist_name": "Alan Jackson",
                    "track_uri": "spotify:track:7aVQ0taICJBg5uscNK1KMN",
                    "track_name": "Livin' On Love"
                },
                {
                    "artist_name": "Alan Jackson",
                    "track_uri": "spotify:track:25Iq3dnxn8jkuZvub6I2ye",
                    "track_name": "There Goes"
                },
                {
                    "artist_name": "Brooks & Dunn",
                    "track_uri": "spotify:track:4L9TrvjOnUjOVqPusbCQfs",
                    "track_name": "Ain't Nothing 'Bout You"
                },
                {
                    "artist_name": "George Strait",
                    "track_uri": "spotify:track:19PJ75UGKjpBo0muDNyxPW",
                    "track_name": "Give It All We Got Tonight"
                },
                {
                    "artist_name": "George Strait",
                    "track_uri": "spotify:track:1qHRFZE8qykNXYZadzmi1m",
                    "track_name": "Give It Away"
                },
                {
                    "artist_name": "Cory Morrow",
                    "track_uri": "spotify:track:0iHF3Xi44HnqsLPeITG12r",
                    "track_name": "Twenty One Days - Live"
                },
                {
                    "artist_name": "Eli Young Band",
                    "track_uri": "spotify:track:0BIIVWkv7nRdYKCNxQUbfh",
                    "track_name": "Oklahoma Girl"
                },
                {
                    "artist_name": "Brooks & Dunn",
                    "track_uri": "spotify:track:5Kbe0XPwG5JLQxjPEqAM20",
                    "track_name": "Red Dirt Road"
                },
                {
                    "artist_name": "George Strait",
                    "track_uri": "spotify:track:2DmBuFsXx1Pd5FHrMF8PD8",
                    "track_name": "It Just Comes Natural"
                },
                {
                    "artist_name": "George Strait",
                    "track_uri": "spotify:track:1FWAB1KZHJnAeET0288xha",
                    "track_name": "Wrapped"
                },
                {
                    "artist_name": "Easton Corbin",
                    "track_uri": "spotify:track:5qNkZdbdfL9tQm1ppZmUrW",
                    "track_name": "Lovin' You Is Fun"
                },
                {
                    "artist_name": "John Denver",
                    "track_uri": "spotify:track:2xYlyywNgefLCRDG8hlxZq",
                    "track_name": "Take Me Home, Country Roads"
                },
                {
                    "artist_name": "Josh Turner",
                    "track_uri": "spotify:track:2rg3yLJKN5Yl4JCHHkMgeC",
                    "track_name": "Time Is Love"
                },
                {
                    "artist_name": "Pat Green",
                    "track_uri": "spotify:track:2HieRfsSSwQA1JUtfmRNgo",
                    "track_name": "Carry On"
                },
                {
                    "artist_name": "Pat Green",
                    "track_uri": "spotify:track:3MJAcAAYwcSvTkecG03FtM",
                    "track_name": "Take Me Out To A Dancehall"
                },
                {
                    "artist_name": "Randy Rogers Band",
                    "track_uri": "spotify:track:1EHNNWLiWe1PJADKEnMvIr",
                    "track_name": "Buy Myself A Chance"
                },
                {
                    "artist_name": "Randy Rogers Band",
                    "track_uri": "spotify:track:3bZKIfJVpW8HktEafRnRP2",
                    "track_name": "Kiss Me In The Dark"
                },
                {
                    "artist_name": "Randy Rogers Band",
                    "track_uri": "spotify:track:4hFSl2YfBUCY7RgZ8OhwCO",
                    "track_name": "In My Arms Instead"
                },
                {
                    "artist_name": "Randy Rogers Band",
                    "track_uri": "spotify:track:43DZiCs70UbYwEHLA3S6Z8",
                    "track_name": "Interstate"
                },
                {
                    "artist_name": "Randy Rogers Band",
                    "track_uri": "spotify:track:40bGMy05duKN7Q8MZuZvAm",
                    "track_name": "Better Than I Ought To Be"
                },
                {
                    "artist_name": "Randy Rogers Band",
                    "track_uri": "spotify:track:5ViyVu6KE35bj1jdQyTfFD",
                    "track_name": "When The Circus Leaves Town"
                },
                {
                    "artist_name": "Randy Rogers Band",
                    "track_uri": "spotify:track:16eibvpajRMveV2v1pY8Rk",
                    "track_name": "She's Actin' Single (I'm Drinkin' Doubles)"
                },
                {
                    "artist_name": "Randy Rogers Band",
                    "track_uri": "spotify:track:6y9liNIMMq5X8v8uiSe4WO",
                    "track_name": "Hill Country"
                },
                {
                    "artist_name": "Lynyrd Skynyrd",
                    "track_uri": "spotify:track:6kZFIsYCBeuH0f1zGk1UoM",
                    "track_name": "Simple Man"
                },
                {
                    "artist_name": "Lynyrd Skynyrd",
                    "track_uri": "spotify:track:4CJVkjo5WpmUAKp3R44LNb",
                    "track_name": "Sweet Home Alabama"
                },
                {
                    "artist_name": "Turnpike Troubadours",
                    "track_uri": "spotify:track:0CsT3gRGhXrMRUBxwgMFNk",
                    "track_name": "1968"
                },
                {
                    "artist_name": "Turnpike Troubadours",
                    "track_uri": "spotify:track:7bhxi9mJDqUbl8ns9Ksr04",
                    "track_name": "Down on Washington"
                },
                {
                    "artist_name": "Turnpike Troubadours",
                    "track_uri": "spotify:track:4EGbPc7wiuVozk9YmLUYqa",
                    "track_name": "Shreveport"
                },
                {
                    "artist_name": "Turnpike Troubadours",
                    "track_uri": "spotify:track:4mFpJB7ZpE8tNRmXW31MK0",
                    "track_name": "Come November"
                },
                {
                    "artist_name": "Turnpike Troubadours",
                    "track_uri": "spotify:track:79QYGruWwuNp5EZ7ZCo7iJ",
                    "track_name": "Wrecked"
                },
                {
                    "artist_name": "Turnpike Troubadours",
                    "track_uri": "spotify:track:0pghPocTwFg6ckBUs52SQ8",
                    "track_name": "Good Lord Lorrie"
                },
                {
                    "artist_name": "Trampled By Turtles",
                    "track_uri": "spotify:track:3E3UOcGshSmvAsO7fqDazr",
                    "track_name": "Wait So Long"
                },
                {
                    "artist_name": "Lynyrd Skynyrd",
                    "track_uri": "spotify:track:64sn7wgJfeQKY3Jisnl59w",
                    "track_name": "Tuesday's Gone"
                },
                {
                    "artist_name": "Eli Young Band",
                    "track_uri": "spotify:track:6JIeedN6tRWMDF91c7DHgo",
                    "track_name": "Highways and Broken Hearts"
                },
                {
                    "artist_name": "Charlie Robison",
                    "track_uri": "spotify:track:13WxL3gtXqI3CI7TlYDLqP",
                    "track_name": "My Hometown"
                },
                {
                    "artist_name": "Whiskey Myers",
                    "track_uri": "spotify:track:391R7sGZ4SX7qPdpAsfiGW",
                    "track_name": "Ballad Of A Southern Man"
                },
                {
                    "artist_name": "Charlie Robison",
                    "track_uri": "spotify:track:5o6sSAGtypSJgErN0IOKYm",
                    "track_name": "New year's day"
                },
                {
                    "artist_name": "Greg Bates",
                    "track_uri": "spotify:track:1TKXEcpmuV3FIOvzVHsTeR",
                    "track_name": "Did It For The Girl"
                },
                {
                    "artist_name": "Cross Canadian Ragweed",
                    "track_uri": "spotify:track:4FQzzwIeTCHl1J26Zv0oZo",
                    "track_name": "Whiskey River"
                },
                {
                    "artist_name": "Wade Bowen",
                    "track_uri": "spotify:track:5Yhr9lHjyM5SXBPU3Ynthu",
                    "track_name": "Saturday Night"
                },
                {
                    "artist_name": "Easton Corbin",
                    "track_uri": "spotify:track:6XD3HMATLswheYevIfKkSi",
                    "track_name": "All Over The Road"
                },
                {
                    "artist_name": "Charlie Robison",
                    "track_uri": "spotify:track:5nnWNHuNfxbVlSCIQ6whOv",
                    "track_name": "Sunset Boulevard"
                },
                {
                    "artist_name": "Cory Morrow",
                    "track_uri": "spotify:track:3MMg3QWezAklnG6ExC14e2",
                    "track_name": "Lead Me On"
                },
                {
                    "artist_name": "Pat Green",
                    "track_uri": "spotify:track:0Tkd0luh6Ulrib7TQFpKca",
                    "track_name": "Whiskey"
                },
                {
                    "artist_name": "Clay Walker",
                    "track_uri": "spotify:track:7njoWVpJbAiTkyT6rKwbze",
                    "track_name": "If I Could Make A Living"
                },
                {
                    "artist_name": "Clay Walker",
                    "track_uri": "spotify:track:56QOJkmoUmuCbu8lPWxur9",
                    "track_name": "She Won't Be Lonely Long"
                },
                {
                    "artist_name": "Clay Walker",
                    "track_uri": "spotify:track:39B9IpMNTUDOzW0JuVHlq4",
                    "track_name": "Live Until I Die"
                },
                {
                    "artist_name": "Clay Walker",
                    "track_uri": "spotify:track:07B6MaqZx1mLfstSzcUVRC",
                    "track_name": "Dreaming with My Eyes Open"
                },
                {
                    "artist_name": "Travis Tritt",
                    "track_uri": "spotify:track:3oW6SWwGqiZSPTiAp7ZQoH",
                    "track_name": "It's A Great Day To Be Alive"
                },
                {
                    "artist_name": "Bart Crow Band",
                    "track_uri": "spotify:track:5ntwkX5Rv86plUMTBdBx1o",
                    "track_name": "All I Need"
                },
                {
                    "artist_name": "Blackberry Smoke",
                    "track_uri": "spotify:track:7DlENkBgvybu7rgnz5TyWb",
                    "track_name": "Good One Comin' on"
                },
                {
                    "artist_name": "Roger Creager",
                    "track_uri": "spotify:track:5H2VJLVLiXlLStv4McVSZG",
                    "track_name": "The Everclear Song"
                },
                {
                    "artist_name": "Roger Creager",
                    "track_uri": "spotify:track:2oW0pJTTGXk2Q0ChlxSfy2",
                    "track_name": "Long way to Mexico"
                },
                {
                    "artist_name": "Reckless Kelly",
                    "track_uri": "spotify:track:22HHKW1Z3NhxUFV0tOV6Iv",
                    "track_name": "Wicked Twisted Road"
                },
                {
                    "artist_name": "Cory Morrow",
                    "track_uri": "spotify:track:6hB8fIfziLeVhpPr2G0OlC",
                    "track_name": "Beer"
                },
                {
                    "artist_name": "Micky & The Motorcars",
                    "track_uri": "spotify:track:4kmGxo98VGOO8xbbYmf3xt",
                    "track_name": "Carolina Morning"
                },
                {
                    "artist_name": "Joe Nichols",
                    "track_uri": "spotify:track:6IC6VhpV7D8T1t037Atqpu",
                    "track_name": "Tequila Makes Her Clothes Fall Off"
                },
                {
                    "artist_name": "Mark Chesnutt",
                    "track_uri": "spotify:track:0D5L0ZxGyhEFTqhfiXwYxw",
                    "track_name": "It's A Little Too Late - 1996 Greatest Hits Version"
                },
                {
                    "artist_name": "Old Crow Medicine Show",
                    "track_uri": "spotify:track:359krpyCKcFF8SFvqWES9L",
                    "track_name": "Wagon Wheel"
                },
                {
                    "artist_name": "Stoney LaRue",
                    "track_uri": "spotify:track:3b9FS4tWpy63wsBHYQ5Lmq",
                    "track_name": "Oklahoma Breakdown"
                },
                {
                    "artist_name": "Turnpike Troubadours",
                    "track_uri": "spotify:track:4zy6xlWANPl54pCEZMgMso",
                    "track_name": "Evangeline"
                },
                {
                    "artist_name": "Cory Morrow",
                    "track_uri": "spotify:track:6HjO2jXfuOEDMwCofEYmPR",
                    "track_name": "Lonesome"
                },
                {
                    "artist_name": "Tim McGraw",
                    "track_uri": "spotify:track:29AR5X5yKPd4DBIAiqUMDy",
                    "track_name": "Southern Girl"
                },
                {
                    "artist_name": "Blake Shelton",
                    "track_uri": "spotify:track:7haN4XreV4WkoBQmkYM709",
                    "track_name": "Drink On It"
                },
                {
                    "artist_name": "Turnpike Troubadours",
                    "track_uri": "spotify:track:4ISJGDIMTOdl1ykRfALjUz",
                    "track_name": "Morgan Street"
                },
                {
                    "artist_name": "Turnpike Troubadours",
                    "track_uri": "spotify:track:2Ed2l31pnYh2gfptoOC4kk",
                    "track_name": "Blue Star"
                },
                {
                    "artist_name": "Turnpike Troubadours",
                    "track_uri": "spotify:track:0lgEHMFEcJGN10nBQCbyVQ",
                    "track_name": "Angola"
                },
                {
                    "artist_name": "Reckless Kelly",
                    "track_uri": "spotify:track:1esj1LFgfyFRbU5brtALfE",
                    "track_name": "Crazy Eddie's Last Hurrah"
                },
                {
                    "artist_name": "Whiskey Myers",
                    "track_uri": "spotify:track:5lcVmjJq1IrGYxpVLB0oKk",
                    "track_name": "Lonely East TX Nights"
                },
                {
                    "artist_name": "Old Crow Medicine Show",
                    "track_uri": "spotify:track:3kp1DqoICwe4Vhf2zVzpUW",
                    "track_name": "Methamphetamine"
                },
                {
                    "artist_name": "Old Crow Medicine Show",
                    "track_uri": "spotify:track:1lzbFHMZ21ErYSr1CHwnxU",
                    "track_name": "Levi"
                },
                {
                    "artist_name": "Reckless Kelly",
                    "track_uri": "spotify:track:5Ycx0AGDOp2el1rVuW3KqV",
                    "track_name": "Give It A Try"
                },
                {
                    "artist_name": "Reckless Kelly",
                    "track_uri": "spotify:track:4bmFmRdQYyzGCSVIW9uhu3",
                    "track_name": "Pennsylvania Avenue"
                },
                {
                    "artist_name": "Cody Johnson",
                    "track_uri": "spotify:track:5EDt7cxNUAVK0QlGjPo1dZ",
                    "track_name": "Texas Kind Of Way"
                },
                {
                    "artist_name": "Reckless Kelly",
                    "track_uri": "spotify:track:6pJPPQpSYCRosNh4ATx9Dv",
                    "track_name": "Weatherbeaten Soul"
                },
                {
                    "artist_name": "Pat Green",
                    "track_uri": "spotify:track:6QNv3VTtuIMO9T0wPbIjZz",
                    "track_name": "Don't Break My Heart Again"
                },
                {
                    "artist_name": "Randy Rogers Band",
                    "track_uri": "spotify:track:3NSVLImz3IDgNe80SNFDxf",
                    "track_name": "Compano Bay"
                },
                {
                    "artist_name": "Stoney LaRue",
                    "track_uri": "spotify:track:3LuPGVkVZ2P3DSEukSJVO6",
                    "track_name": "Velvet"
                },
                {
                    "artist_name": "Steve Earle",
                    "track_uri": "spotify:track:1KnilWyiAb1Jwa9QJXZGMN",
                    "track_name": "The Galway Girl"
                },
                {
                    "artist_name": "Ray Wylie Hubbard",
                    "track_uri": "spotify:track:4Jmqv2LJW0tML1cKZ3uoEA",
                    "track_name": "Screw You, We're From Texas"
                },
                {
                    "artist_name": "Easton Corbin",
                    "track_uri": "spotify:track:7bNX2Fgb4MjPrYbkHaCNwV",
                    "track_name": "Roll With It"
                },
                {
                    "artist_name": "Cory Morrow",
                    "track_uri": "spotify:track:2C9fwRYFM3UdejPT91qgXw",
                    "track_name": "He Carries Me"
                },
                {
                    "artist_name": "Reckless Kelly",
                    "track_uri": "spotify:track:6gBGabSA0PrRIPQxGHlu4b",
                    "track_name": "Good Luck & True Love"
                },
                {
                    "artist_name": "The Damn Quails",
                    "track_uri": "spotify:track:5DppLYav0k9u1vB59Y8uPA",
                    "track_name": "Midnight Swagger"
                },
                {
                    "artist_name": "Pat Green",
                    "track_uri": "spotify:track:49NQ7G2L4YaaU70GRlAmxX",
                    "track_name": "Somewhere Between Texas and Mexico"
                },
                {
                    "artist_name": "Robert Earl Keen",
                    "track_uri": "spotify:track:2cBhtkCAxCehKpHI8a695Q",
                    "track_name": "Something I Do"
                },
                {
                    "artist_name": "William Clark Green",
                    "track_uri": "spotify:track:38iGqJQPZcTYNx6bdR5YWC",
                    "track_name": "She Likes the Beatles"
                },
                {
                    "artist_name": "William Clark Green",
                    "track_uri": "spotify:track:5sUSgckr5AREtLdIpt9CMO",
                    "track_name": "It's About Time"
                },
                {
                    "artist_name": "Steve Earle",
                    "track_uri": "spotify:track:4sD5C8vtuPtblOYanu3jSc",
                    "track_name": "Your Still Standin' There"
                },
                {
                    "artist_name": "Steve Earle",
                    "track_uri": "spotify:track:7fF6Af2M3vL4IUtE8cMy6G",
                    "track_name": "Feel Alright"
                },
                {
                    "artist_name": "Whiskey Myers",
                    "track_uri": "spotify:track:2xAT2FrRnlmVuc2XYCmxW2",
                    "track_name": "Dogwood"
                },
                {
                    "artist_name": "Cody Johnson",
                    "track_uri": "spotify:track:4rW9EUFaMSNVY8JhbqrB6z",
                    "track_name": "Me and My Kind"
                },
                {
                    "artist_name": "Whiskey Myers",
                    "track_uri": "spotify:track:7oE8dFBb6AtemPMkwsz1ET",
                    "track_name": "Broken Window Serenade"
                },
                {
                    "artist_name": "Alan Jackson",
                    "track_uri": "spotify:track:4VyTESM8Uovi8ZpOBgNPev",
                    "track_name": "Little Bitty"
                },
                {
                    "artist_name": "Alan Jackson",
                    "track_uri": "spotify:track:38hbQ1wHHBNXDpPGJRMY28",
                    "track_name": "Drive (For Daddy Gene)"
                },
                {
                    "artist_name": "Steve Earle",
                    "track_uri": "spotify:track:7aXK1UkGw6bDc2zr4YUpdJ",
                    "track_name": "Hard-Core Troubadour"
                },
                {
                    "artist_name": "Charlie Robison",
                    "track_uri": "spotify:track:38dPLjUSNPXEvI6PbmW9ha",
                    "track_name": "Beautiful Day"
                },
                {
                    "artist_name": "Charlie Robison",
                    "track_uri": "spotify:track:5siqT4KJmvRYXDYUV62zpz",
                    "track_name": "Feelin' Good"
                },
                {
                    "artist_name": "Charlie Robison",
                    "track_uri": "spotify:track:6Et0nYrxtA0QQucMPLHXan",
                    "track_name": "Big City Blues"
                },
                {
                    "artist_name": "Merle Haggard",
                    "track_uri": "spotify:track:0MeiAClcqNNrdLUosiyVl6",
                    "track_name": "Mama Tried"
                },
                {
                    "artist_name": "Charlie Robison",
                    "track_uri": "spotify:track:6homYLJ2nbF5izfEbRrfVC",
                    "track_name": "Barlight"
                },
                {
                    "artist_name": "Rodney Crowell",
                    "track_uri": "spotify:track:576MasCmcO40iuwFltsKe5",
                    "track_name": "Fever on the Bayou"
                },
                {
                    "artist_name": "The Damn Quails",
                    "track_uri": "spotify:track:3TMUdD9vE4DoqDYi7VXStt",
                    "track_name": "Fool's Gold"
                },
                {
                    "artist_name": "Wood & Wire",
                    "track_uri": "spotify:track:78uGbesFxxy5yGSritKIsw",
                    "track_name": "Bet the World"
                },
                {
                    "artist_name": "The Damn Quails",
                    "track_uri": "spotify:track:3EwifLbB45SRIDDhtkHR3b",
                    "track_name": "Better Place to Stop"
                },
                {
                    "artist_name": "Wood & Wire",
                    "track_uri": "spotify:track:7307QYKawIFiCVX5BWpfyk",
                    "track_name": "Mexico"
                },
                {
                    "artist_name": "Cory Morrow",
                    "track_uri": "spotify:track:5MkzpSjnJo0EcrkdDJritI",
                    "track_name": "The Light On The Stage (Sing With Me)"
                },
                {
                    "artist_name": "Parker McCollum",
                    "track_uri": "spotify:track:2OoDlxJ3mP8UTDGLMhK02x",
                    "track_name": "Meet you in the Middle"
                },
                {
                    "artist_name": "Parker McCollum",
                    "track_uri": "spotify:track:2knxQXkBzNVsNp8fMzePtl",
                    "track_name": "New Orleans"
                },
                {
                    "artist_name": "Steve Earle",
                    "track_uri": "spotify:track:6EtQxcfkQqVibxsUr718YA",
                    "track_name": "Guitar Town"
                },
                {
                    "artist_name": "Sturgill Simpson",
                    "track_uri": "spotify:track:3loDAi9IiqxUrV7rRXlzDN",
                    "track_name": "A Little Light Within"
                },
                {
                    "artist_name": "Sturgill Simpson",
                    "track_uri": "spotify:track:0st2bvgDqkOHGkjUjbyADM",
                    "track_name": "You Can Have The Crown"
                },
                {
                    "artist_name": "Stoney LaRue",
                    "track_uri": "spotify:track:2bMuWWA7X0OvJzbUXjOGyP",
                    "track_name": "Travelin' Kind"
                },
                {
                    "artist_name": "Ray Wylie Hubbard",
                    "track_uri": "spotify:track:2RwvzezSWXAbq87BeUzXSn",
                    "track_name": "The Beauty Way"
                },
                {
                    "artist_name": "Turnpike Troubadours",
                    "track_uri": "spotify:track:6VxU7gm1T8lweKyTv4qUlr",
                    "track_name": "Down Here"
                },
                {
                    "artist_name": "Robert Earl Keen",
                    "track_uri": "spotify:track:4NpYrBb5iuDqW1S5qrU3b6",
                    "track_name": "Feelin' Good Again"
                },
                {
                    "artist_name": "Zac Brown Band",
                    "track_uri": "spotify:track:1qwnPVOIJjAFfCc40Etb1D",
                    "track_name": "Homegrown"
                },
                {
                    "artist_name": "Parker McCollum",
                    "track_uri": "spotify:track:5iYKnmjIuI9OZhiAI9f5Mc",
                    "track_name": "Happy New Year"
                },
                {
                    "artist_name": "Parker McCollum",
                    "track_uri": "spotify:track:08cIbmO7i95tiLAvbCsjC3",
                    "track_name": "Galveston Bay"
                },
                {
                    "artist_name": "Parker McCollum",
                    "track_uri": "spotify:track:06FVPdUiZphZ8ZQU2vD5bQ",
                    "track_name": "Silhouette"
                },
                {
                    "artist_name": "Robert Earl Keen",
                    "track_uri": "spotify:track:4uY5Ha1kmPqMoBiDWyHQr3",
                    "track_name": "I Gotta Go"
                },
                {
                    "artist_name": "The Damn Quails",
                    "track_uri": "spotify:track:6C2uJqVaRue5UcUoHaZvwP",
                    "track_name": "Tough Luck / Cryin' Shame"
                },
                {
                    "artist_name": "Charlie Robison",
                    "track_uri": "spotify:track:4hWl96lv13MPIOrh89bJm6",
                    "track_name": "John O'Reilly"
                },
                {
                    "artist_name": "Matt Kimbrow",
                    "track_uri": "spotify:track:3SINJuVv0yOYIePodRgxwW",
                    "track_name": "Livin' the Good Life"
                },
                {
                    "artist_name": "Stoney LaRue",
                    "track_uri": "spotify:track:3C4Tj4ZGDdAKXehan6M1ml",
                    "track_name": "Golden Shackles"
                },
                {
                    "artist_name": "Reckless Kelly",
                    "track_uri": "spotify:track:0miUJi8VEVpoBKfgB9dQrg",
                    "track_name": "The Girl I Knew"
                },
                {
                    "artist_name": "Stoney LaRue",
                    "track_uri": "spotify:track:0SlysNrQuxEMuV7AtsyM02",
                    "track_name": "Easy She Comes"
                },
                {
                    "artist_name": "The Damn Quails",
                    "track_uri": "spotify:track:1rS5NbLnwwwj7IcvPbcpUs",
                    "track_name": "California Open Invitation"
                },
                {
                    "artist_name": "The Damn Quails",
                    "track_uri": "spotify:track:3EJzvyUe2GrEkYPWBiZ5TS",
                    "track_name": "Out of the Birdcage"
                },
                {
                    "artist_name": "Cory Morrow",
                    "track_uri": "spotify:track:4NBIUrapth4WWjpFl4W7uq",
                    "track_name": "Good Intentions"
                },
                {
                    "artist_name": "Wade Bowen",
                    "track_uri": "spotify:track:36cmw1oeo5fkzOMTBMRxY6",
                    "track_name": "Sun Shines on a Dreamer"
                },
                {
                    "artist_name": "Mike Ryan",
                    "track_uri": "spotify:track:2xikoxCRIG2AFv8VXEdVjE",
                    "track_name": "Girls I Date"
                },
                {
                    "artist_name": "Sturgill Simpson",
                    "track_uri": "spotify:track:3XKigKMmykb4HLH10oOhBr",
                    "track_name": "Life Aint Fair And The World Is Mean"
                },
                {
                    "artist_name": "Ryan Bingham",
                    "track_uri": "spotify:track:0GmGxMJcYcxPGBYQPn3oaY",
                    "track_name": "Bread & Water"
                },
                {
                    "artist_name": "Stoney LaRue",
                    "track_uri": "spotify:track:1YzmbIq3q2XO5LL7ATbctF",
                    "track_name": "First One To Know"
                },
                {
                    "artist_name": "Uncle Lucius",
                    "track_uri": "spotify:track:2nypm37dKGdS6TGLYF4Sd0",
                    "track_name": "Don't Own the Right"
                },
                {
                    "artist_name": "The Dirty Guv'nahs",
                    "track_uri": "spotify:track:5FAtSoItsFeWRCDDyTGHon",
                    "track_name": "Fairlane"
                },
                {
                    "artist_name": "George Strait",
                    "track_uri": "spotify:track:5Q851iZNbt0aq3fP9Kik76",
                    "track_name": "Here For A Good Time"
                },
                {
                    "artist_name": "The Damn Quails",
                    "track_uri": "spotify:track:6WCGE1ReEcBssoxnwoErVH",
                    "track_name": "Just a Little While"
                },
                {
                    "artist_name": "Bart Crow",
                    "track_uri": "spotify:track:5L0tWEyEwO4x7lH3G74ZnU",
                    "track_name": "Top of Rock Bottom"
                },
                {
                    "artist_name": "George Strait",
                    "track_uri": "spotify:track:23WjeJQCrtKxvf6u3OAxH1",
                    "track_name": "Take Me To Texas"
                },
                {
                    "artist_name": "George Strait",
                    "track_uri": "spotify:track:7a2NUtKR5wLMmu7tayiLp1",
                    "track_name": "Let It Go"
                },
                {
                    "artist_name": "Jason Boland & The Stragglers",
                    "track_uri": "spotify:track:04yO1WqGaIxTk3QJIVyncw",
                    "track_name": "Pearl Snaps"
                },
                {
                    "artist_name": "Cody Johnson",
                    "track_uri": "spotify:track:2g3vpJiqwswGJbUOSkCWqC",
                    "track_name": "Dance Her Home"
                },
                {
                    "artist_name": "Reckless Kelly",
                    "track_uri": "spotify:track:6AHEV4xWdbfURSSExpvwR6",
                    "track_name": "A Guy Like Me"
                },
                {
                    "artist_name": "Reckless Kelly",
                    "track_uri": "spotify:track:5SBUEN78iDzhasOSDhnOeT",
                    "track_name": "Bird on a Wire"
                },
                {
                    "artist_name": "Reckless Kelly",
                    "track_uri": "spotify:track:0Xk7y4Qt9nN4DnA6BzV1Er",
                    "track_name": "Bulletproof"
                },
                {
                    "artist_name": "Charlie Robison",
                    "track_uri": "spotify:track:3ForwY7F7RxmJB0PlX8Fxg",
                    "track_name": "Life of the Party"
                },
                {
                    "artist_name": "Alan Jackson",
                    "track_uri": "spotify:track:6QBgavY97XKKkDA4nrVT9D",
                    "track_name": "You Can Always Come Home"
                },
                {
                    "artist_name": "Ryan Bingham",
                    "track_uri": "spotify:track:6aLl1AjRbo4ddJZh7Hzazx",
                    "track_name": "Southside Of Heaven"
                },
                {
                    "artist_name": "Ryan Bingham",
                    "track_uri": "spotify:track:7vekU2vBq0w52MRD2waBay",
                    "track_name": "Nobody Knows My Trouble"
                },
                {
                    "artist_name": "Wade Bowen",
                    "track_uri": "spotify:track:5M2Gfbf4Akuhq6jZEwEYLS",
                    "track_name": "When I Woke up Today"
                },
                {
                    "artist_name": "Clint Black",
                    "track_uri": "spotify:track:5o5f7CWLRsUAT8NqYUEJcq",
                    "track_name": "Time For That"
                },
                {
                    "artist_name": "Red Shahan",
                    "track_uri": "spotify:track:1pdcT9aojZHINvpccuyegA",
                    "track_name": "Southern Man"
                },
                {
                    "artist_name": "Brett Eldredge",
                    "track_uri": "spotify:track:3un2KQUaQ2brEpd8dK93wI",
                    "track_name": "Beat Of The Music"
                },
                {
                    "artist_name": "Billy Currington",
                    "track_uri": "spotify:track:4iLPK8QnOvqm0Azbsk2GDn",
                    "track_name": "Don't It"
                },
                {
                    "artist_name": "Bart Crow",
                    "track_uri": "spotify:track:2vDjB0Ggq0XLWafCG9WFQs",
                    "track_name": "Dear Music,"
                },
                {
                    "artist_name": "Maren Morris",
                    "track_uri": "spotify:track:1LM5zQv5pBKPyO7rm7Uz6U",
                    "track_name": "My Church"
                },
                {
                    "artist_name": "Reckless Kelly",
                    "track_uri": "spotify:track:4CZrDF50zES5KDHmZbX2BG",
                    "track_name": "Seven Nights In Eire"
                },
                {
                    "artist_name": "Reckless Kelly",
                    "track_uri": "spotify:track:018vie7GqsC02TuXjz2Rch",
                    "track_name": "American Blood"
                },
                {
                    "artist_name": "Wade Bowen",
                    "track_uri": "spotify:track:17dwiQdacJbguupIX7GnVE",
                    "track_name": "West Texas Rain"
                },
                {
                    "artist_name": "John Baumann",
                    "track_uri": "spotify:track:3cv7omxHpRSeB1BhVFVNte",
                    "track_name": "Vices"
                },
                {
                    "artist_name": "Sturgill Simpson",
                    "track_uri": "spotify:track:1cRc03E5Ps0fwe4l8fz2J0",
                    "track_name": "Brace For Impact (Live A Little)"
                },
                {
                    "artist_name": "James McMurtry",
                    "track_uri": "spotify:track:2jG8qg7KDYWKm9smYCXz1i",
                    "track_name": "Copper Canteen"
                },
                {
                    "artist_name": "Parker McCollum",
                    "track_uri": "spotify:track:0truUh0a6al3dkuCqDisAj",
                    "track_name": "The Tune"
                },
                {
                    "artist_name": "Miranda Lambert",
                    "track_uri": "spotify:track:4Qtw0HNKSbIRT5sWUnbRXc",
                    "track_name": "Vice"
                },
                {
                    "artist_name": "Sturgill Simpson",
                    "track_uri": "spotify:track:7dtLQIK9vxQ22A6X8jiceA",
                    "track_name": "Some Days"
                },
                {
                    "artist_name": "Hayes Carll",
                    "track_uri": "spotify:track:64c0o7We5e7rete26iTZS1",
                    "track_name": "Beaumont"
                },
                {
                    "artist_name": "Kevin Fowler",
                    "track_uri": "spotify:track:0rk6JE7ODyGWWquK4y7t1u",
                    "track_name": "That Girl"
                }
            ],
            "num_edits": 73,
            "duration_ms": 41654045,
            "num_artists": 62
        }
    ]
}